powershift/__init__.py
powershift/cli/__init__.py
powershift/cli/completion-bash.sh
powershift/composer/__init__.py
powershift/endpoints/__init__.py
powershift/endpoints/api.py
powershift/endpoints/base.py
powershift/resources/__init__.py
powershift/resources/base.py
powershift/resources/types.py
powershift/templates/resources/BuildConfig.json
powershift/templates/resources/DeploymentConfig.json
powershift/templates/resources/ImageStream.json
powershift/templates/resources/PersistentVolumeClaim.json
powershift/templates/resources/Route.json
powershift/templates/resources/Service.json
powershift-1.3.7.dist-info/DESCRIPTION.rst
powershift-1.3.7.dist-info/METADATA
powershift-1.3.7.dist-info/RECORD
powershift-1.3.7.dist-info/WHEEL
powershift-1.3.7.dist-info/entry_points.txt
powershift-1.3.7.dist-info/metadata.json
powershift-1.3.7.dist-info/top_level.txt
