Metadata-Version: 2.0
Name: powershift
Version: 1.3.7
Summary: Python library for working with OpenShift.
Home-page: https://github.com/getwarped/powershift
Author: Graham Dumpleton
Author-email: Graham.Dumpleton@gmail.com
License: BSD
Keywords: openshift kubernetes
Platform: UNKNOWN
Classifier: Development Status :: 4 - Beta
Classifier: License :: OSI Approved :: BSD License
Classifier: Programming Language :: Python :: 3
Classifier: Programming Language :: Python :: 3.5
Requires-Dist: Jinja2
Requires-Dist: requests
Requires-Dist: aiohttp
Requires-Dist: click
